{
    "Reservations": [
        {
            "Groups": [],
            "Instances": [
                {
                    "AmiLaunchIndex": 0,
                    "ImageId": "ami-0e4a83a73c3504fe3",
                    "InstanceId": "i-0fad3b305b130f40a",
                    "InstanceType": "m5.16xlarge",
                    "KeyName": "Mushin2",
                    "LaunchTime": "2024-09-05T19:04:57+00:00",
                    "Monitoring": {
                        "State": "disabled"
                    },
                    "Placement": {
                        "AvailabilityZone": "us-east-2a",
                        "GroupName": "",
                        "Tenancy": "default"
                    },
                    "PrivateDnsName": "ip-172-31-0-96.us-east-2.compute.internal",
                    "PrivateIpAddress": "172.31.0.96",
                    "ProductCodes": [],
                    "PublicDnsName": "ec2-3-137-10-187.us-east-2.compute.amazonaws.com",
                    "PublicIpAddress": "3.137.10.187",
                    "State": {
                        "Code": 80,
                        "Name": "stopped"
                    },
                    "StateTransitionReason": "User initiated (2024-09-05 19:20:46 GMT)",
                    "SubnetId": "subnet-27a5404c",
                    "VpcId": "vpc-5777853c",
                    "Architecture": "x86_64",
                    "BlockDeviceMappings": [
                        {
                            "DeviceName": "/dev/xvda",
                            "Ebs": {
                                "AttachTime": "2024-07-10T20:32:00+00:00",
                                "DeleteOnTermination": true,
                                "Status": "attached",
                                "VolumeId": "vol-0bd5d73f4276b053f"
                            }
                        }
                    ],
                    "ClientToken": "59752317-46db-4267-9c89-af64edccded5",
                    "EbsOptimized": true,
                    "EnaSupport": true,
                    "Hypervisor": "xen",
                    "IamInstanceProfile": {
                        "Arn": "arn:aws:iam::535362115856:instance-profile/EC2_Spot",
                        "Id": "AIPAXZJQRTEIJBVDDE6S6"
                    },
                    "InstanceLifecycle": "spot",
                    "NetworkInterfaces": [
                        {
                            "Association": {
                                "IpOwnerId": "535362115856",
                                "PublicDnsName": "ec2-3-137-10-187.us-east-2.compute.amazonaws.com",
                                "PublicIp": "3.137.10.187"
                            },
                            "Attachment": {
                                "AttachTime": "2024-07-10T20:31:59+00:00",
                                "AttachmentId": "eni-attach-067a4fc3e6c8ed210",
                                "DeleteOnTermination": true,
                                "DeviceIndex": 0,
                                "Status": "attached",
                                "NetworkCardIndex": 0
                            },
                            "Description": "",
                            "Groups": [
                                {
                                    "GroupName": "default",
                                    "GroupId": "sg-fe79549c"
                                }
                            ],
                            "Ipv6Addresses": [],
                            "MacAddress": "02:7a:90:6e:64:0d",
                            "NetworkInterfaceId": "eni-03cd1f33b006daf78",
                            "OwnerId": "535362115856",
                            "PrivateDnsName": "ip-172-31-0-96.us-east-2.compute.internal",
                            "PrivateIpAddress": "172.31.0.96",
                            "PrivateIpAddresses": [
                                {
                                    "Association": {
                                        "IpOwnerId": "535362115856",
                                        "PublicDnsName": "ec2-3-137-10-187.us-east-2.compute.amazonaws.com",
                                        "PublicIp": "3.137.10.187"
                                    },
                                    "Primary": true,
                                    "PrivateDnsName": "ip-172-31-0-96.us-east-2.compute.internal",
                                    "PrivateIpAddress": "172.31.0.96"
                                }
                            ],
                            "SourceDestCheck": true,
                            "Status": "in-use",
                            "SubnetId": "subnet-27a5404c",
                            "VpcId": "vpc-5777853c",
                            "InterfaceType": "interface"
                        }
                    ],
                    "RootDeviceName": "/dev/xvda",
                    "RootDeviceType": "ebs",
                    "SecurityGroups": [
                        {
                            "GroupName": "default",
                            "GroupId": "sg-fe79549c"
                        }
                    ],
                    "SourceDestCheck": true,
                    "SpotInstanceRequestId": "sir-rnn6wdwk",
                    "StateReason": {
                        "Code": "Client.UserInitiatedShutdown",
                        "Message": "Client.UserInitiatedShutdown: User initiated shutdown"
                    },
                    "Tags": [
                        {
                            "Key": "Name",
                            "Value": "Feng Shui"
                        }
                    ],
                    "VirtualizationType": "hvm",
                    "CpuOptions": {
                        "CoreCount": 32,
                        "ThreadsPerCore": 2
                    },
                    "CapacityReservationSpecification": {
                        "CapacityReservationPreference": "open"
                    },
                    "HibernationOptions": {
                        "Configured": false
                    },
                    "MetadataOptions": {
                        "State": "applied",
                        "HttpTokens": "optional",
                        "HttpPutResponseHopLimit": 1,
                        "HttpEndpoint": "enabled",
                        "HttpProtocolIpv6": "disabled",
                        "InstanceMetadataTags": "disabled"
                    },
                    "EnclaveOptions": {
                        "Enabled": false
                    },
                    "PlatformDetails": "Linux/UNIX",
                    "UsageOperation": "RunInstances",
                    "UsageOperationUpdateTime": "2024-07-10T20:31:59+00:00",
                    "PrivateDnsNameOptions": {
                        "HostnameType": "ip-name",
                        "EnableResourceNameDnsARecord": true,
                        "EnableResourceNameDnsAAAARecord": false
                    },
                    "MaintenanceOptions": {
                        "AutoRecovery": "default"
                    },
                    "CurrentInstanceBootMode": "legacy-bios"
                }
            ],
            "OwnerId": "535362115856",
            "ReservationId": "r-05a85afe52acb00a1"
        }
    ]
}
